MANIFEST.in
README
README.md
setup.py
raduga/__init__.py
raduga/config.py
raduga/distmgr.py
raduga/main.py
raduga/pcli.py
raduga.egg-info/PKG-INFO
raduga.egg-info/SOURCES.txt
raduga.egg-info/dependency_links.txt
raduga.egg-info/entry_points.txt
raduga.egg-info/not-zip-safe
raduga.egg-info/requires.txt
raduga.egg-info/top_level.txt
raduga/aws/__init__.py
raduga/aws/cfn.py
raduga/aws/ec2.py
raduga/cfn/build_stack.cfn.py