Metadata-Version: 1.1
Name: raduga
Version: 0.0.8
Summary: Infrastructure-as-code framework for AWS
Home-page: http://github.com/tuxpiper/raduga
Author: David Losada Carballo
Author-email: david@tuxpiper.com
License: MIT
Keywords: aws internet cloud infrastructure deployment automation
Platform: UNKNOWN
Classifier: Development Status :: 2 - Pre-Alpha
Classifier: Topic :: System
Classifier: Environment :: Console
Classifier: Intended Audience :: System Administrators
Classifier: License :: OSI Approved :: MIT License
Classifier: Programming Language :: Python
